vid2frames/LICENSE
vid2frames/README.MD
vid2frames/__init__.py
vid2frames/requirements.txt
vid2frames/thirdparty.json
vid2frames-0.10.dist-info/LICENSE.rst
vid2frames-0.10.dist-info/METADATA
vid2frames-0.10.dist-info/WHEEL
vid2frames-0.10.dist-info/top_level.txt
vid2frames-0.10.dist-info/RECORD
